setup.py
dmontjoy/Binomialdistribution.py
dmontjoy/Gaussiandistribution.py
dmontjoy/Generaldistribution.py
dmontjoy/__init__.py
dmontjoy.egg-info/PKG-INFO
dmontjoy.egg-info/SOURCES.txt
dmontjoy.egg-info/dependency_links.txt
dmontjoy.egg-info/not-zip-safe
dmontjoy.egg-info/top_level.txt