Metadata-Version: 1.0
Name: dmontjoy
Version: 0.1
Summary: Gaussian distributions
Home-page: UNKNOWN
Author: daniel montjoy
Author-email: dmontjoy@gmail.com
License: UNKNOWN
Platform: UNKNOWN
